did_peer_4-0.1.3.dist-info/METADATA
did_peer_4-0.1.3.dist-info/WHEEL
did_peer_4-0.1.3.dist-info/licenses/LICENSE
did_peer_4/__init__.py
did_peer_4/input_doc.py
did_peer_4/valid.py
did_peer_4-0.1.3.dist-info/RECORD
