Metadata-Version: 2.1
Name: did-peer-4
Version: 0.1.3
Summary: An implementation of did:peer:4
Author-Email: Daniel Bluhm <dbluhm@pm.me>
License: Apache-2.0
Requires-Python: >=3.9
Requires-Dist: base58>=2.1.1
